adversarial_testing/__init__.py
adversarial_testing/adversarial_runner.py
adversarial_testing/blind_validator.py
adversarial_testing/content_preservation.py
adversarial_testing/cost_estimator.py
adversarial_testing/enhanced_runner.py
adversarial_testing/epistemic_metrics.py
adversarial_testing/mission_drift_validator.py
adversarial_testing/mutation_testing.py
adversarial_testing/phase_aware_drift.py
adversarial_testing/phase_aware_validator.py
adversarial_testing/property_testing.py
adversarial_testing/red_team_agent.py
adversarial_testing/resilience.py
adversarial_testing/vulnerability_database.py
atlasforge_enhancements/__init__.py
atlasforge_enhancements/atlasforge_enhancer.py
atlasforge_enhancements/bias_detector.py
atlasforge_enhancements/context_healing.py
atlasforge_enhancements/exploration_graph.py
atlasforge_enhancements/fingerprint_extractor.py
atlasforge_enhancements/insight_extractor.py
atlasforge_enhancements/knowledge_transfer.py
atlasforge_enhancements/mission_continuity_tracker.py
atlasforge_enhancements/scaffold_calibrator.py
atlasforge_enhancements/scaffold_library.py
dashboard_modules/__init__.py
dashboard_modules/analytics.py
dashboard_modules/artifact_health.py
dashboard_modules/atlasforge.py
dashboard_modules/bundle_version.py
dashboard_modules/cache.py
dashboard_modules/core.py
dashboard_modules/investigation.py
dashboard_modules/knowledge_base.py
dashboard_modules/queue_scheduler.py
dashboard_modules/recovery.py
dashboard_modules/semantic.py
dashboard_modules/services.py
dashboard_modules/url_handlers.py
dashboard_modules/version_checker.py
dashboard_modules/workspace_resolver.py
ai_atlasforge-1.6.7.dist-info/LICENSE
ai_atlasforge-1.6.7.dist-info/METADATA
ai_atlasforge-1.6.7.dist-info/WHEEL
ai_atlasforge-1.6.7.dist-info/entry_points.txt
ai_atlasforge-1.6.7.dist-info/top_level.txt
ai_atlasforge-1.6.7.dist-info/RECORD
