Metadata-Version: 2.2
Name: ai-atlasforge
Version: 1.6.7
Summary: Autonomous AI research and development platform powered by Claude
License: MIT
Project-URL: Homepage, https://github.com/DragonShadows1978/AI-AtlasForge
Project-URL: Documentation, https://github.com/DragonShadows1978/AI-AtlasForge#readme
Project-URL: Repository, https://github.com/DragonShadows1978/AI-AtlasForge.git
Project-URL: Issues, https://github.com/DragonShadows1978/AI-AtlasForge/issues
Keywords: ai,claude,autonomous,research,development
Classifier: Development Status :: 4 - Beta
Classifier: Environment :: Console
Classifier: Environment :: Web Environment
Classifier: Intended Audience :: Developers
Classifier: License :: OSI Approved :: MIT License
Classifier: Operating System :: POSIX :: Linux
Classifier: Programming Language :: Python :: 3
Classifier: Programming Language :: Python :: 3.10
Classifier: Programming Language :: Python :: 3.11
Classifier: Programming Language :: Python :: 3.12
Classifier: Topic :: Scientific/Engineering :: Artificial Intelligence
Classifier: Topic :: Software Development :: Code Generators
Requires-Python: >=3.10
License-File: LICENSE
Requires-Dist: flask>=2.0.0
Requires-Dist: flask-socketio>=5.0.0
Requires-Dist: simple-websocket>=0.5.0
Requires-Dist: anthropic>=0.18.0
Requires-Dist: watchdog>=3.0.0
Requires-Dist: psutil>=5.9.0
Requires-Dist: numpy>=1.21.0
Requires-Dist: scikit-learn>=1.0.0
Provides-Extra: dev
Requires-Dist: pytest>=7.0.0; extra == "dev"
Requires-Dist: pytest-cov>=4.0.0; extra == "dev"
Requires-Dist: black>=23.0.0; extra == "dev"
Requires-Dist: flake8>=6.0.0; extra == "dev"
Requires-Dist: mypy>=1.0.0; extra == "dev"
Provides-Extra: tray
Requires-Dist: PyGObject>=3.42.0; extra == "tray"
Provides-Extra: all
Requires-Dist: ai-atlasforge[dev,tray]; extra == "all"
